AUTHORS.rst
CONTRIBUTING.rst
HISTORY.rst
LICENSE
MANIFEST.in
README.rst
setup.cfg
setup.py
docs/Makefile
docs/authors.rst
docs/conf.py
docs/contributing.rst
docs/history.rst
docs/index.rst
docs/installation.rst
docs/make.bat
docs/readme.rst
docs/usage.rst
ewspy/__init__.py
ewspy/cli.py
ewspy/ewspy.py
ewspy.egg-info/PKG-INFO
ewspy.egg-info/SOURCES.txt
ewspy.egg-info/dependency_links.txt
ewspy.egg-info/entry_points.txt
ewspy.egg-info/not-zip-safe
ewspy.egg-info/requires.txt
ewspy.egg-info/top_level.txt
tests/__init__.py
tests/test_ewspy.py