Metadata-Version: 1.1
Name: ewspy
Version: 0.1.0
Summary: Exchange Web Service in Python
Home-page: https://github.com/kdheepak/ewspy
Author: Dheepak Krishnamurthy
Author-email: kdheepak89@gmail.com
License: MIT license
Keywords: ewspy
Platform: UNKNOWN
Classifier: Development Status :: 2 - Pre-Alpha
Classifier: Intended Audience :: Developers
Classifier: License :: OSI Approved :: MIT License
Classifier: Natural Language :: English
Classifier: Programming Language :: Python :: 2
Classifier: Programming Language :: Python :: 2.6
Classifier: Programming Language :: Python :: 2.7
Classifier: Programming Language :: Python :: 3
Classifier: Programming Language :: Python :: 3.3
Classifier: Programming Language :: Python :: 3.4
Classifier: Programming Language :: Python :: 3.5
